{
  "_generated": "from 17 historical WhatsApp supplier chats (timestamp mining)",
  "_note": "Baseline supplier behaviour. The exec overlays live WhatsAppMessage data as it accumulates. Keyed by normalised supplier name.",
  "suppliers": {
    "bbm": {
      "supplier": "BBM",
      "replyMedianMins": 25,
      "replySpeed": "normal",
      "oosEvents": 0,
      "oosRatePct": 0.0,
      "reliability": "high",
      "docCount": 157,
      "docMedianMins": 121,
      "docPeakHour": 4,
      "activePeakHour": 4,
      "supMsgs": 439,
      "spanDays": 1368
    },
    "bgs": {
      "supplier": "BGS",
      "replyMedianMins": 2,
      "replySpeed": "fast",
      "oosEvents": 10,
      "oosRatePct": 2.3,
      "reliability": "medium",
      "docCount": 73,
      "docMedianMins": 13,
      "docPeakHour": 8,
      "activePeakHour": 10,
      "supMsgs": 427,
      "spanDays": 1474
    },
    "beansco": {
      "supplier": "BeansCo",
      "replyMedianMins": 12,
      "replySpeed": "normal",
      "oosEvents": 0,
      "oosRatePct": 0.0,
      "reliability": "high",
      "docCount": 119,
      "docMedianMins": 32,
      "docPeakHour": 11,
      "activePeakHour": 11,
      "supMsgs": 781,
      "spanDays": 1474
    },
    "blancoz": {
      "supplier": "Blancoz",
      "replyMedianMins": 2,
      "replySpeed": "fast",
      "oosEvents": 3,
      "oosRatePct": 0.4,
      "reliability": "high",
      "docCount": 172,
      "docMedianMins": 45,
      "docPeakHour": 11,
      "activePeakHour": 11,
      "supMsgs": 673,
      "spanDays": 951
    },
    "cakediscovery": {
      "supplier": "Cake Discovery",
      "replyMedianMins": 23,
      "replySpeed": "normal",
      "oosEvents": 0,
      "oosRatePct": 0.0,
      "reliability": "high",
      "docCount": 269,
      "docMedianMins": 36,
      "docPeakHour": 12,
      "activePeakHour": 12,
      "supMsgs": 805,
      "spanDays": 844
    },
    "collective": {
      "supplier": "Collective",
      "replyMedianMins": 10,
      "replySpeed": "fast",
      "oosEvents": 1,
      "oosRatePct": 0.2,
      "reliability": "high",
      "docCount": 55,
      "docMedianMins": 30,
      "docPeakHour": 10,
      "activePeakHour": 1,
      "supMsgs": 501,
      "spanDays": 1473
    },
    "dankoff": {
      "supplier": "Dankoff",
      "replyMedianMins": 10,
      "replySpeed": "fast",
      "oosEvents": 9,
      "oosRatePct": 0.9,
      "reliability": "high",
      "docCount": 320,
      "docMedianMins": 14,
      "docPeakHour": 11,
      "activePeakHour": 11,
      "supMsgs": 1009,
      "spanDays": 1475
    },
    "gcr": {
      "supplier": "GCR",
      "replyMedianMins": 1,
      "replySpeed": "fast",
      "oosEvents": 1,
      "oosRatePct": 0.4,
      "reliability": "high",
      "docCount": 94,
      "docMedianMins": 16,
      "docPeakHour": 5,
      "activePeakHour": 5,
      "supMsgs": 223,
      "spanDays": 188
    },
    "hnj": {
      "supplier": "HNJ",
      "replyMedianMins": 3,
      "replySpeed": "fast",
      "oosEvents": 0,
      "oosRatePct": 0.0,
      "reliability": "high",
      "docCount": 25,
      "docMedianMins": 1,
      "docPeakHour": 12,
      "activePeakHour": 11,
      "supMsgs": 67,
      "spanDays": 113
    },
    "jgpacific": {
      "supplier": "JG Pacific",
      "replyMedianMins": 5,
      "replySpeed": "fast",
      "oosEvents": 13,
      "oosRatePct": 1.5,
      "reliability": "medium",
      "docCount": 322,
      "docMedianMins": 3,
      "docPeakHour": 4,
      "activePeakHour": 4,
      "supMsgs": 839,
      "spanDays": 762
    },
    "jsbreadserie": {
      "supplier": "JS Breadserie",
      "replyMedianMins": 37,
      "replySpeed": "slow",
      "oosEvents": 0,
      "oosRatePct": 0.0,
      "reliability": "high",
      "docCount": 201,
      "docMedianMins": 92,
      "docPeakHour": 10,
      "activePeakHour": 10,
      "supMsgs": 832,
      "spanDays": 628
    },
    "jijus": {
      "supplier": "Jiju’s",
      "replyMedianMins": 6,
      "replySpeed": "fast",
      "oosEvents": 0,
      "oosRatePct": 0.0,
      "reliability": "high",
      "docCount": 197,
      "docMedianMins": 4,
      "docPeakHour": 9,
      "activePeakHour": 11,
      "supMsgs": 489,
      "spanDays": 280
    },
    "milkmoka": {
      "supplier": "Milk Moka",
      "replyMedianMins": 12,
      "replySpeed": "normal",
      "oosEvents": 2,
      "oosRatePct": 0.5,
      "reliability": "high",
      "docCount": 93,
      "docMedianMins": 38,
      "docPeakHour": 10,
      "activePeakHour": 10,
      "supMsgs": 434,
      "spanDays": 571
    },
    "richs": {
      "supplier": "RICH’s",
      "replyMedianMins": 22,
      "replySpeed": "normal",
      "oosEvents": 0,
      "oosRatePct": 0.0,
      "reliability": "high",
      "docCount": 25,
      "docMedianMins": 18,
      "docPeakHour": 10,
      "activePeakHour": 9,
      "supMsgs": 98,
      "spanDays": 140
    },
    "unique": {
      "supplier": "Unique",
      "replyMedianMins": 7,
      "replySpeed": "fast",
      "oosEvents": 10,
      "oosRatePct": 1.5,
      "reliability": "medium",
      "docCount": 138,
      "docMedianMins": 17,
      "docPeakHour": 12,
      "activePeakHour": 11,
      "supMsgs": 647,
      "spanDays": 1475
    },
    "xora2025k": {
      "supplier": "Xora 2025K",
      "replyMedianMins": 4,
      "replySpeed": "fast",
      "oosEvents": 0,
      "oosRatePct": 0.0,
      "reliability": "high",
      "docCount": 34,
      "docMedianMins": 32,
      "docPeakHour": 3,
      "activePeakHour": 3,
      "supMsgs": 205,
      "spanDays": 504
    },
    "yowseng": {
      "supplier": "Yow Seng",
      "replyMedianMins": 3,
      "replySpeed": "fast",
      "oosEvents": 10,
      "oosRatePct": 2.5,
      "reliability": "medium",
      "docCount": 112,
      "docMedianMins": 13,
      "docPeakHour": 11,
      "activePeakHour": 11,
      "supMsgs": 394,
      "spanDays": 170
    }
  }
}